plantpathoppi_ml/__init__.py
plantpathoppi_ml/prediction.py
plantpathoppi_ml/rf_ld.pkl
plantpathoppi_ml/svm_ac.pkl
plantpathoppi_ml/svm_ct.pkl
plantpathoppi_ml-0.0.1.dist-info/LICENSE.txt
plantpathoppi_ml-0.0.1.dist-info/METADATA
plantpathoppi_ml-0.0.1.dist-info/WHEEL
plantpathoppi_ml-0.0.1.dist-info/top_level.txt
plantpathoppi_ml-0.0.1.dist-info/RECORD
